{
  "bdr:10977": {
    "datetime": "2016-10-25 16:48:09.310600", 
    "delete_result": 200
  }, 
  "bdr:10993": {
    "datetime": "2016-10-25 16:48:08.527694", 
    "delete_result": 200
  }, 
  "bdr:10996": {
    "datetime": "2016-10-25 16:48:08.445989", 
    "delete_result": 200
  }, 
  "bdr:200389": {
    "datetime": "2016-10-25 16:48:08.911858", 
    "delete_result": 200
  }, 
  "bdr:298470": {
    "datetime": "2016-10-25 16:48:08.215696", 
    "delete_result": 200
  }, 
  "bdr:298520": {
    "datetime": "2016-10-25 16:48:08.968638", 
    "delete_result": 200
  }, 
  "bdr:298528": {
    "datetime": "2016-10-25 16:48:09.277774", 
    "delete_result": 200
  }, 
  "bdr:298533": {
    "datetime": "2016-10-25 16:48:10.018234", 
    "delete_result": 200
  }, 
  "bdr:298534": {
    "datetime": "2016-10-25 16:48:09.988166", 
    "delete_result": 200
  }, 
  "bdr:298535": {
    "datetime": "2016-10-25 16:48:09.952929", 
    "delete_result": 200
  }, 
  "bdr:298536": {
    "datetime": "2016-10-25 16:48:09.925726", 
    "delete_result": 200
  }, 
  "bdr:298537": {
    "datetime": "2016-10-25 16:48:09.898323", 
    "delete_result": 200
  }, 
  "bdr:298562": {
    "datetime": "2016-10-25 16:48:09.339078", 
    "delete_result": 200
  }, 
  "bdr:298619": {
    "datetime": "2016-10-25 16:48:09.543491", 
    "delete_result": 200
  }, 
  "bdr:298620": {
    "datetime": "2016-10-25 16:48:08.649356", 
    "delete_result": 200
  }, 
  "bdr:298904": {
    "datetime": "2016-10-25 16:48:08.489413", 
    "delete_result": 200
  }, 
  "bdr:298905": {
    "datetime": "2016-10-25 16:48:08.553903", 
    "delete_result": 200
  }, 
  "bdr:298906": {
    "datetime": "2016-10-25 16:48:09.625470", 
    "delete_result": 200
  }, 
  "bdr:298907": {
    "datetime": "2016-10-25 16:48:09.651729", 
    "delete_result": 200
  }, 
  "bdr:298908": {
    "datetime": "2016-10-25 16:48:09.452938", 
    "delete_result": 200
  }, 
  "bdr:298909": {
    "datetime": "2016-10-25 16:48:09.366778", 
    "delete_result": 200
  }, 
  "bdr:298910": {
    "datetime": "2016-10-25 16:48:08.717398", 
    "delete_result": 200
  }, 
  "bdr:298911": {
    "datetime": "2016-10-25 16:48:08.688594", 
    "delete_result": 200
  }, 
  "bdr:298912": {
    "datetime": "2016-10-25 16:48:08.776662", 
    "delete_result": 200
  }, 
  "bdr:298913": {
    "datetime": "2016-10-25 16:48:08.745617", 
    "delete_result": 200
  }, 
  "bdr:298914": {
    "datetime": "2016-10-25 16:48:08.831948", 
    "delete_result": 200
  }, 
  "bdr:298915": {
    "datetime": "2016-10-25 16:48:08.805462", 
    "delete_result": 200
  }, 
  "bdr:298916": {
    "datetime": "2016-10-25 16:48:08.884600", 
    "delete_result": 200
  }, 
  "bdr:298917": {
    "datetime": "2016-10-25 16:48:08.858032", 
    "delete_result": 200
  }, 
  "bdr:298918": {
    "datetime": "2016-10-25 16:48:08.620790", 
    "delete_result": 200
  }, 
  "bdr:298919": {
    "datetime": "2016-10-25 16:48:08.580662", 
    "delete_result": 200
  }, 
  "bdr:298920": {
    "datetime": "2016-10-25 16:48:09.170896", 
    "delete_result": 200
  }, 
  "bdr:298921": {
    "datetime": "2016-10-25 16:48:09.422110", 
    "delete_result": 200
  }, 
  "bdr:298922": {
    "datetime": "2016-10-25 16:48:09.681914", 
    "delete_result": 200
  }, 
  "bdr:298923": {
    "datetime": "2016-10-25 16:48:09.517227", 
    "delete_result": 200
  }, 
  "bdr:298924": {
    "datetime": "2016-10-25 16:48:09.571211", 
    "delete_result": 200
  }, 
  "bdr:298925": {
    "datetime": "2016-10-25 16:48:09.870930", 
    "delete_result": 200
  }, 
  "bdr:299541": {
    "datetime": "2016-10-25 16:48:08.292002", 
    "delete_result": 200
  }, 
  "bdr:299542": {
    "datetime": "2016-10-25 16:48:08.372810", 
    "delete_result": 200
  }, 
  "bdr:299543": {
    "datetime": "2016-10-25 16:48:08.345861", 
    "delete_result": 200
  }, 
  "bdr:299544": {
    "datetime": "2016-10-25 16:48:07.714457", 
    "delete_result": 200
  }, 
  "bdr:299545": {
    "datetime": "2016-10-25 16:48:07.677714", 
    "delete_result": 200
  }, 
  "bdr:299546": {
    "datetime": "2016-10-25 16:48:08.261447", 
    "delete_result": 200
  }, 
  "bdr:299547": {
    "datetime": "2016-10-25 16:48:09.118366", 
    "delete_result": 200
  }, 
  "bdr:299805": {
    "datetime": "2016-10-25 16:48:09.752922", 
    "delete_result": 200
  }, 
  "bdr:299806": {
    "datetime": "2016-10-25 16:48:09.783301", 
    "delete_result": 200
  }, 
  "bdr:299807": {
    "datetime": "2016-10-25 16:48:09.810931", 
    "delete_result": 200
  }, 
  "bdr:300128": {
    "datetime": "2016-10-25 16:48:09.843187", 
    "delete_result": 200
  }, 
  "bdr:300984": {
    "datetime": "2016-10-25 16:48:09.243039", 
    "delete_result": 200
  }, 
  "bdr:405441": {
    "datetime": "2016-10-25 16:48:09.197599", 
    "delete_result": 200
  }, 
  "bdr:405515": {
    "datetime": "2016-10-25 16:48:07.569450", 
    "delete_result": 200
  }, 
  "bdr:405518": {
    "datetime": "2016-10-25 16:48:08.316740", 
    "delete_result": 200
  }, 
  "bdr:405521": {
    "datetime": "2016-10-25 16:48:08.995806", 
    "delete_result": 200
  }, 
  "bdr:405522": {
    "datetime": "2016-10-25 16:48:09.022892", 
    "delete_result": 200
  }, 
  "bdr:405523": {
    "datetime": "2016-10-25 16:48:09.058866", 
    "delete_result": 200
  }, 
  "bdr:405524": {
    "datetime": "2016-10-25 16:48:09.089981", 
    "delete_result": 200
  }, 
  "bdr:405525": {
    "datetime": "2016-10-25 16:48:09.711116", 
    "delete_result": 200
  }, 
  "bdr:405526": {
    "datetime": "2016-10-25 16:48:09.144329", 
    "delete_result": 200
  }, 
  "bdr:405529": {
    "datetime": "2016-10-25 16:48:08.940988", 
    "delete_result": 200
  }, 
  "bdr:405530": {
    "datetime": "2016-10-25 16:48:10.100807", 
    "delete_result": 200
  }, 
  "bdr:405531": {
    "datetime": "2016-10-25 16:48:10.073606", 
    "delete_result": 200
  }, 
  "bdr:405532": {
    "datetime": "2016-10-25 16:48:10.045369", 
    "delete_result": 200
  }, 
  "bdr:405533": {
    "datetime": "2016-10-25 16:48:09.597446", 
    "delete_result": 200
  }, 
  "bdr:405534": {
    "datetime": "2016-10-25 16:48:09.489764", 
    "delete_result": 200
  }, 
  "bdr:405535": {
    "datetime": "2016-10-25 16:48:09.394052", 
    "delete_result": 200
  }
}